maskarade/__init__.py
maskarade/connector.py
maskarade/log.py
maskarade/manager.py
maskarade/model.py
maskarade/reference.py
maskarade/utils.py
maskarade-1.0.0.dist-info/METADATA
maskarade-1.0.0.dist-info/WHEEL
maskarade-1.0.0.dist-info/licenses/LICENSE
maskarade-1.0.0.dist-info/RECORD
