Metadata-Version: 2.4
Name: maskarade
Version: 1.0.0
Summary: A simple model to build structured interfaces.
Project-URL: Repository, https://github.com/stickm4n/maskarade
Project-URL: Documentation, https://github.com/stickm4n/maskarade/wiki
Project-URL: Issues, https://github.com/stickm4n/maskarade/issues
Author-email: "Julio C. Galindo" <jcgalindo.jcgh@gmail.com>
License: MIT License
License-File: LICENSE
Keywords: interface,model
Classifier: Development Status :: 5 - Production/Stable
Classifier: Intended Audience :: Developers
Classifier: License :: OSI Approved :: MIT License
Classifier: Operating System :: OS Independent
Classifier: Programming Language :: Python :: 3
Classifier: Programming Language :: Python :: 3.9
Classifier: Programming Language :: Python :: 3.10
Classifier: Programming Language :: Python :: 3.11
Classifier: Programming Language :: Python :: 3.12
Classifier: Programming Language :: Python :: 3.13
Requires-Python: >=3.9
